hydra_plugins/hydra_joblib_launcher/__init__.py
hydra_plugins/hydra_joblib_launcher/_core.py
hydra_plugins/hydra_joblib_launcher/config.py
hydra_plugins/hydra_joblib_launcher/joblib_launcher.py
hydra_joblib_launcher-1.2.0.dist-info/METADATA
hydra_joblib_launcher-1.2.0.dist-info/WHEEL
hydra_joblib_launcher-1.2.0.dist-info/top_level.txt
hydra_joblib_launcher-1.2.0.dist-info/RECORD
